{"Date Made Public": "2010-12-13", "date": "2010-12-13", "Company": "Liberty Tax Service", "City": "Portsmouth", "State": "Virginia", "Type of breach": "PHYS", "Type of organization": "BSF", "Total Records": 0, "Description of incident": "Personal tax documents were left exposed in a dumpster.  The tax documents had Social Security numbers, addresses and financial information.  The company did not reveal how the documents may have found their way into the dumpster, but said that it was against company policy to leave them exposed and intact. At least one person had their tax information from 2008 exposed.\u00a0 The number of documents was described as \"mounds\".", "Information Source": "Databreaches.net", "Source URL": "", "Year of Breach": 2010, "Latitude": 36.835426, "Longitude": -76.298274}