{"Date Made Public": "2011-01-18", "date": "2011-01-18", "Company": "Iowa Telecommunications, Experian", "City": "Newtown", "State": "Iowa", "Type of breach": "UNKN", "Type of organization": "BSO", "Total Records": 0, "Description of incident": "One of Experian's clients experienced a breach that gave unauthorized users access to Experian's pool of consumer names, Social Security numbers, dates of birth and account numbers. \u00a0Someone gained access to the Experian login information for Iowa Telecommunications and was able to obtain consumer report information in the company's name.", "Information Source": "Databreaches.net", "Source URL": "", "Year of Breach": 2011, "Latitude": 40.376401, "Longitude": -93.334937}