{"Date Made Public": "2011-02-02", "date": "2011-02-02", "Company": "University Book Exchange", "City": "Greenville", "State": "North Carolina", "Type of breach": "CARD", "Type of organization": "BSR", "Total Records": 100, "Description of incident": "People who used their credit or debit cards to make purchases at the University Book Exchange may have had their financial information taken.  A number of victims have contacted the police, but investigators are still not completely sure that the source of the fraudulent activity is a breach at the U.B.E. store. All or nearly all of those affected by the breach were connected to East Carolina University.UPDATE\u00a0(2/13/2011): At least 100 East Carolina University students have reported fraudulent charges to their accounts. \u00a0The breach is believed to have occurred between January 5 and 25. \u00a0", "Information Source": "Databreaches.net", "Source URL": "", "Year of Breach": 2011, "Latitude": 35.612661, "Longitude": -77.366354}