{"Date Made Public": "2013-06-27", "date": "2013-06-27", "Company": "Citi Prepaid Services", "City": "New York", "State": "New York", "Type of breach": "DISC", "Type of organization": "BSF", "Total Records": 0, "Description of incident": "A code change in the prepaid cardholder website impacted the security features that authenticate cardholder logins. \u00a0Anyone who logged into the prepaid cardholder website between June 2 and June 13 was affected. \u00a0The issue was remediated and it does not appear that unauthorized charges have occurred on any of the affected accounts.", "Information Source": "California Attorney General", "Source URL": "", "Year of Breach": 2013, "Latitude": 40.712784, "Longitude": -74.005941}