{"Date Made Public": "2013-02-20", "date": "2013-02-20", "Company": "Central Hudson Gas & Electric", "City": "Poughkeepsie", "State": "New York", "Type of breach": "HACK", "Type of organization": "NGO", "Total Records": 110000, "Description of incident": "Central Hudson learned of a cyber attack that occurred over President's Day weekend. \u00a0Customers were notified the day after the holiday and encouraged to monitor their bank accounts and credit reports. \u00a0Customer banking information and other personal information may have been accessed during the attack.", "Information Source": "Databreaches.net", "Source URL": "", "Year of Breach": 2013, "Latitude": 41.700371, "Longitude": -73.92097}