{"Date Made Public": "2013-09-23", "date": "2013-09-23", "Company": "Columbia University Medical Center (CUMC)", "City": "New York", "State": "New York", "Type of breach": "DISC", "Type of organization": "MED", "Total Records": 407, "Description of incident": "An Excel file with the names and Social Security numbers of 407 medical students was accidentally attached to an email that was sent to medical students interested in a residency match list. \u00a0The Excel column that contained the Social Security numbers was hidden and still accessible. \u00a0The issue was discovered in March for the 2013 list and it was later discovered that the same issue had occurred in 2008 and 2009.", "Information Source": "Databreaches.net", "Source URL": "", "Year of Breach": 2013, "Latitude": 40.712784, "Longitude": -74.005941}