{"Date Made Public": "2005-01-18", "date": "2005-01-18", "Company": "University of California, San Diego", "City": "San Diego", "State": "California", "Type of breach": "HACK", "Type of organization": "EDU", "Total Records": 3500, "Description of incident": "A hacker breached the security of two University computers that stored the Social Security numbers and names of students and alumni of UCSD Extension.", "Information Source": "Dataloss DB", "Source URL": "", "Year of Breach": 2005, "Latitude": 32.715329, "Longitude": -117.157255}