{"Date Made Public": "2013-11-20", "date": "2013-11-20", "Company": "Office of Dr. Kathleen Whisman", "City": "Sebastopol", "State": "California", "Type of breach": "STAT", "Type of organization": "MED", "Total Records": 0, "Description of incident": "Sometime around April 11, 2013, Dr. Whisman learned of a breach that involved patient information on a computer recovered during an identity theft ring investigation. \u00a0The patient information included full names, Social Security numbers, addresses, telephone numbers, dates of birth, and insurance plan information for patients who were seen in 1998 and 1999. \u00a0The information likely came from a stolen computer and Dr. Whisman was encouraged to delay notification until the investigation was completed.", "Information Source": "California Attorney General", "Source URL": "", "Year of Breach": 2013, "Latitude": 38.402136, "Longitude": -122.823881}