{"Date Made Public": "2005-08-30", "date": "2005-08-30", "Company": "JP Morgan Chase & Co.", "City": "Dallas", "State": "Texas", "Type of breach": "PORT", "Type of organization": "BSF", "Total Records": 0, "Description of incident": "A laptop was stolen on August 8th.\u00a0 It contained              personal and financial account information of customers.\u00a0 Those affected were contacted.", "Information Source": "Dataloss DB", "Source URL": "", "Year of Breach": 2005, "Latitude": 32.802955, "Longitude": -96.769923}