{"Date Made Public": "2005-10-21", "date": "2005-10-21", "Company": "Wilcox Memorial Hospital", "City": "Lihue", "State": "Hawaii", "Type of breach": "PORT", "Type of organization": "MED", "Total Records": 130000, "Description of incident": "A backup computer data drive containing medical record numbers, addresses, names and Social Security numbers of current and former patients was lost.\u00a0 Letters have been sent to affected patients.", "Information Source": "Dataloss DB", "Source URL": "", "Year of Breach": 2005, "Latitude": 21.981111, "Longitude": -159.371111}