{"Date Made Public": "2006-05-12", "date": "2006-05-12", "Company": "Mercantile Potomac Bank", "City": "Gaithersburg", "State": "Maryland", "Type of breach": "PORT", "Type of organization": "BSF", "Total Records": 48000, "Description of incident": "A laptop containing confidential              information about customers, including Social Security numbers and              account numbers was stolen when a bank employee removed it from the              premises, in violation of the bank's policies. The computer did not              contain customer passwords, personal identification numbers (PIN numbers)              or account expiration dates. The bank contacted affected customers and offered them one year of free credit monitoring services.", "Information Source": "Dataloss DB", "Source URL": "", "Year of Breach": 2006, "Latitude": 39.143441, "Longitude": -77.201371}