{"Date Made Public": "2006-06-23", "date": "2006-06-23", "Company": "CBCInnovis Inc., Andover Bank", "City": "Conneaut", "State": "Ohio", "Type of breach": "UNKN", "Type of organization": "BSF", "Total Records": 1122, "Description of incident": "Names, Social Security numbers, addresses, names of creditors, account numbers, payment histories and public records of financial judgments may have been accessed without proper authorization at Andover Bank.", "Information Source": "Dataloss DB", "Source URL": "", "Year of Breach": 2006, "Latitude": 41.947555, "Longitude": -80.554241}