{"Date Made Public": "2006-06-27", "date": "2006-06-27", "Company": "Empire Beauty School Inc.", "City": "Brooklyn", "State": "New York", "Type of breach": "PHYS", "Type of organization": "EDU", "Total Records": 1132, "Description of incident": "The June 20 theft of a briefcase from an administrative employee's vehicle caused reports with the names and Social Security numbers of former students to be lost. A laptop was also stolen during the burglary, but it is unlikely that it had personal information.", "Information Source": "Dataloss DB", "Source URL": "", "Year of Breach": 2006, "Latitude": 40.65, "Longitude": -73.95}