{"Date Made Public": "2006-08-18", "date": "2006-08-18", "Company": "Experian, LA Walker Company", "City": "Roseville", "State": "California", "Type of breach": "HACK", "Type of organization": "BSF", "Total Records": 30, "Description of incident": "Thirty New York residents and an unknown number of customers nationwide had their information accessed. \u00a0The unauthorized access by an Experian client resulted in the exposure of names, dates of birth, account numbers, Social Security numbers and addresses.", "Information Source": "Dataloss DB", "Source URL": "", "Year of Breach": 2006, "Latitude": 38.752124, "Longitude": -121.288006}