{"Date Made Public": "2006-10-06", "date": "2006-10-06", "Company": "Camp Pendleton Marine Corps base via Lincoln B.P. Management", "City": "Camp Pendleton", "State": "California", "Type of breach": "PORT", "Type of organization": "GOV", "Total Records": 2400, "Description of incident": "A laptop missing from Lincoln              B.P. Management Inc. holds personally identifiable data about 2,400              Camp Pendleton residents.", "Information Source": "Dataloss DB", "Source URL": "", "Year of Breach": 2006, "Latitude": 33.36434, "Longitude": -117.408649}