{"Date Made Public": "2006-11-28", "date": "2006-11-28", "Company": "California State University, Los Angeles (Cal State LA), Charter College of Education", "City": "Los Angeles", "State": "California", "Type of breach": "PORT", "Type of organization": "EDU", "Total Records": 2534, "Description of incident": "An employee's USB drive              was inside a purse stolen from a car trunk. It contained personal              information on 48 faculty members and more than 2,500 students and              applicants of a teacher credentialing program. Information included              names, SSNs, campus ID numbers, phone numbers, and e-mail addresses.", "Information Source": "Dataloss DB", "Source URL": "", "Year of Breach": 2006, "Latitude": 34.052234, "Longitude": -118.243685}