{"Date Made Public": "2007-01-11", "date": "2007-01-11", "Company": "University of Idaho", "City": "Moscow", "State": "Idaho", "Type of breach": "STAT", "Type of organization": "EDU", "Total Records": 70000, "Description of incident": "Over Thanksgiving weekend,              3 desktop computers were stolen from the Advancement Services office              containing personal information of alumni, donors, employees, and              students. 331,000 individuals may have been exposed, with as many              as 70,000 records containing SSNs, names and addresses.", "Information Source": "Dataloss DB", "Source URL": "", "Year of Breach": 2007, "Latitude": 0.0, "Longitude": 0.0}