{"Date Made Public": "2007-02-02", "date": "2007-02-02", "Company": "Massachusetts Department of Industrial Accidents", "City": "Boston", "State": "Massachusetts", "Type of breach": "INSD", "Type of organization": "GOV", "Total Records": 1200, "Description of incident": "A former state contractor              allegedly accessed a workers' compensation data file and stole personal              information, including SSNs. The thief used the data to commit identity              theft on at least 3 individuals.", "Information Source": "Dataloss DB", "Source URL": "", "Year of Breach": 2007, "Latitude": 42.358431, "Longitude": -71.059773}