{"Date Made Public": "2007-02-14", "date": "2007-02-14", "Company": "Conneticut Office of the State Comptroller", "City": "Hartford", "State": "Connecticut", "Type of breach": "DISC", "Type of organization": "GOV", "Total Records": 1753, "Description of incident": "Personal information of              state employees including names and Social Security numbers was inadvertently              posted on the Internet in a spreadsheet of vendors used by the state.", "Information Source": "Dataloss DB", "Source URL": "", "Year of Breach": 2007, "Latitude": 41.763711, "Longitude": -72.685093}