{"Date Made Public": "2007-03-07", "date": "2007-03-07", "Company": "Eastern Suffolk BOCES", "City": "Patchogue", "State": "New York", "Type of breach": "HACK", "Type of organization": "GOV", "Total Records": 1500, "Description of incident": "A file server in the Eastern Suffolk BOCES computer area was hacked.  Data from the Free and Reduced Lunch Database was compromised.  The names of parents and children, Social Security numbers, addresses, home and work phone numbers, salary information and income information that were related to the program may have been accessed.", "Information Source": "Dataloss DB", "Source URL": "", "Year of Breach": 2007, "Latitude": 40.765654, "Longitude": -73.015108}