{"Date Made Public": "2007-05-12", "date": "2007-05-12", "Company": "Goshen College", "City": "Goshen", "State": "Indiana", "Type of breach": "HACK", "Type of organization": "EDU", "Total Records": 7300, "Description of incident": "A hacker accessed a college computer that contained the names, addresses, birth dates, Social Security numbers and phone numbers of students and information on some parents with the suspected motivation of using the system to send spam e-mails.", "Information Source": "Dataloss DB", "Source URL": "", "Year of Breach": 2007, "Latitude": 41.582272, "Longitude": -85.834438}