{"Date Made Public": "2007-07-27", "date": "2007-07-27", "Company": "City of Virginia Beach, Flexible Benefits Administrators", "City": "Virginia Beach", "State": "Virginia", "Type of breach": "INSD", "Type of organization": "GOV", "Total Records": 2000, "Description of incident": "A former employee              allegedly stole Virginia Beach city and school district employees'              personal information and used it to commit prescription fraud. Police              discovered a list of names and Social Security numbers at the employee's              home.", "Information Source": "Dataloss DB", "Source URL": "", "Year of Breach": 2007, "Latitude": 36.852926, "Longitude": -75.977985}