{"Date Made Public": "2008-03-05", "date": "2008-03-05", "Company": "Nevada Department of Public Safety", "City": "Carson City", "State": "Nevada", "Type of breach": "PORT", "Type of organization": "GOV", "Total Records": 109, "Description of incident": "A private firm working for the              Nevada Department of Public Safety has lost a thumb drive containing personal information provided              by individuals seeking jobs with the agency. Data included Social              Security numbers, addresses and background check information.", "Information Source": "Dataloss DB", "Source URL": "", "Year of Breach": 2008, "Latitude": 39.163798, "Longitude": -119.767403}