{"Date Made Public": "2008-04-10", "date": "2008-04-10", "Company": "Joliet West High School", "City": "Joliet", "State": "Illinois", "Type of breach": "HACK", "Type of organization": "EDU", "Total Records": 0, "Description of incident": "A student using a school computer              last month was able to access personal information about every student              enrolled. The student allegedly downloaded a list of names and Social              Security numbers to his iPod.", "Information Source": "Dataloss DB", "Source URL": "", "Year of Breach": 2008, "Latitude": 41.525031, "Longitude": -88.081725}