{"Date Made Public": "2008-07-04", "date": "2008-07-04", "Company": "US Army", "City": "Fort Lewis", "State": "Washington", "Type of breach": "PORT", "Type of organization": "GOV", "Total Records": 900, "Description of incident": "A laptop computer that was reported              stolen from an Army employee's truck contained personal information              on Fort Lewis soldiers. A 500 GB removable hard drive was also taken              in the theft. UPDATE             (7/11/08) :A 17-year-old Lacey boy faces a charge of suspicion of              possession of stolen property after Tumwater police uncovered items              from vehicle prowls, including a stolen Army laptop containing information              on Fort Lewis soldiers.", "Information Source": "Dataloss DB", "Source URL": "", "Year of Breach": 2008, "Latitude": 47.086632, "Longitude": -122.611504}