{"Date Made Public": "2008-08-30", "date": "2008-08-30", "Company": "Ohio Police & Fire Pension System", "City": "Columbus", "State": "Ohio", "Type of breach": "INSD", "Type of organization": "GOV", "Total Records": 13000, "Description of incident": "A former mailroom supervisor at              the Ohio Police & Fire Pension System forwarded the names, addresses              and Social Security numbers from his work e-mail address to his personal              e-mail address before quitting his job. The file contains information              for 13,000 of the approximately 24,000 retired members of the Ohio              Police & Fire Pension System, most of whom are former police officers.", "Information Source": "Dataloss DB", "Source URL": "", "Year of Breach": 2008, "Latitude": 39.961176, "Longitude": -82.998794}