{"Date Made Public": "2012-05-29", "date": "2012-05-29", "Company": "Investacorp, Inc.", "City": "Miami", "State": "Florida", "Type of breach": "DISC", "Type of organization": "BSF", "Total Records": 0, "Description of incident": "A vendor of the broker-dealer, National Financial Services (NFS), used by Investacorp was involved in a data security breach. \u00a0On or around March 12, 2012, Investacorp learned that an NFS vendor had inadvertently shared electronic files with another federally regulated broker-dealer that also uses NFS's services. \u00a0The incident occurred on November 29, 2011 and was first noticed on February 13, 2012. The information included client names, Social Security numbers, and certain types of account data. Five Investacorp clients from California may have been affected, but the total number of affected individuals nationwide was not reported. \u00a0The vendor responsible for the mistake worked with the other broker-dealer to delete the client files from their system. Investacorp then received an executed affidavit from the broker-dealer certifying the destruction of the electronic files. \u00a0", "Information Source": "California Attorney General", "Source URL": "", "Year of Breach": 2012, "Latitude": 25.788969, "Longitude": -80.226439}