{"Date Made Public": "2008-12-02", "date": "2008-12-02", "Company": "Florida Agency for Workforce Innovation", "City": "Tallahassee", "State": "Florida", "Type of breach": "DISC", "Type of organization": "GOV", "Total Records": 259193, "Description of incident": "Employment information and more              than a quarter million Social Security numbers were posted online.              The breach occurred when several thousand Excel and text files containing              millions of employment records were posted in the course of developing              a new website.", "Information Source": "Dataloss DB", "Source URL": "", "Year of Breach": 2008, "Latitude": 30.438256, "Longitude": -84.280733}