{"Date Made Public": "2009-03-04", "date": "2009-03-04", "Company": "Elk Grove Unified School District", "City": "Elk Grove", "State": "California", "Type of breach": "PHYS", "Type of organization": "EDU", "Total Records": 520, "Description of incident": "A document with the Social Security            numbers of more than 500 Elk Grove Unified School District employees            was lost by a district employee.", "Information Source": "Dataloss DB", "Source URL": "", "Year of Breach": 2009, "Latitude": 38.408799, "Longitude": -121.371618}