{"Date Made Public": "2009-03-12", "date": "2009-03-12", "Company": "Dezonia Group", "City": "Chicago", "State": "Illinois", "Type of breach": "PORT", "Type of organization": "BSO", "Total Records": 63000, "Description of incident": "The city of Chicago bills people            for ambulance rides -- $600 and up. It uses a third party, Dezonia            Group, for billing. An employee's laptop, containing patient names, addresses            and Social Security numbers, was stolen from the company. Reports differ as to whether or not the data was encrypted. ", "Information Source": "Dataloss DB", "Source URL": "", "Year of Breach": 2009, "Latitude": 41.850033, "Longitude": -87.650052}