{"Date Made Public": "2009-12-04", "date": "2009-12-04", "Company": "University of Nebraska", "City": "Omaha", "State": "Nebraska", "Type of breach": "HACK", "Type of organization": "EDU", "Total Records": 1400, "Description of incident": "A computer in the College of Education and Human Sciences at the Lincoln campus was breached. The security breach was discovered last month at the University of Nebraska involving the names, addresses and Social Security Numbers of 1,400 Hinsdale High School District 86 graduates. The University's investigation revealed the computer had not been adequately secured, allowing unauthorized external access to the computer and its information.", "Information Source": "Dataloss DB", "Source URL": "", "Year of Breach": 2009, "Latitude": 41.254006, "Longitude": -95.999258}