{"Date Made Public": "2009-12-17", "date": "2009-12-17", "Company": "North Carolina Libraries", "City": "Raleigh", "State": "North Carolina", "Type of breach": "HACK", "Type of organization": "EDU", "Total Records": 51000, "Description of incident": "Library users at 25 campuses were the victims of a security breach in August. The libraries collect driver's license and Social Security numbers to help identify computer users. The information is stored on a central server in Raleigh. Other campuses affected are Alamance, Beaufort, Bladen, Blue Ridge, Brunswick, Central Carolina, College of the Albemarle, Gaston, Halifax, Haywood, Lenoir, Martin, Nash, Pamlico, Piedmont, Richmond, Roanoke-Chowan, Rowan-Cabarrus, Sandhills, Southwestern, Tri-County, Vance Granville and Wilson. ", "Information Source": "Dataloss DB", "Source URL": "", "Year of Breach": 2009, "Latitude": 35.772096, "Longitude": -78.638615}