{"Date Made Public": "2009-12-18", "date": "2009-12-18", "Company": "Dickinson School of Law", "City": "Carlisle", "State": "Pennsylvania", "Type of breach": "HACK", "Type of organization": "EDU", "Total Records": 261, "Description of incident": "A computer in the Dickinson School of Law that contained 261 Social Security numbers from an archived class list was found to be infected with malware that enabled it to communicate with an unauthorized computer outside the network.", "Information Source": "Dataloss DB", "Source URL": "", "Year of Breach": 2009, "Latitude": 40.201477, "Longitude": -77.18887}