{"Date Made Public": "2012-03-30", "date": "2012-03-30", "Company": "Public Broadcasting System", "City": "Arlington", "State": "Virginia", "Type of breach": "HACK", "Type of organization": "NGO", "Total Records": 1871, "Description of incident": "A hacker or hackers accessed and published information from a Public Broadcasting System server or database. \u00a0A total of 1,598 press usernames, plain-text passwords, and email addresses were posted online. \u00a0Thirty-six administrator names, usernames, email addresses and passwords were also publicly posted. \u00a0Finally, 237 names, emails, passwords, and usernames from other sources were posted online.", "Information Source": "Dataloss DB", "Source URL": "", "Year of Breach": 2012, "Latitude": 38.87997, "Longitude": -77.10677}