{"Date Made Public": "2013-12-17", "date": "2013-12-17", "Company": "UHS-Pruitt Corporation", "City": "Norcross", "State": "Georgia", "Type of breach": "PORT", "Type of organization": "MED", "Total Records": 1300, "Description of incident": "Current and former residents of Heritage Healthcare of Ashburn, UniHealth Post-Acute Care Augusta Hills, Heritage Healthcare of Fitzgerald, Heritage Healthcare at Osceola, Palmyra Nursing Home and Sylvester Healthcare may have been affected by the September 26 theft of a laptop from an employee's car. \u00a0The laptop contained patient names, Social Security numbers, Medicare numbers, dates of birth, and resident ID numbers.", "Information Source": "HHS via PHIPrivacy.net", "Source URL": "", "Year of Breach": 2013, "Latitude": 33.941213, "Longitude": -84.213531}