{"Date Made Public": "2012-08-07", "date": "2012-08-07", "Company": "Nordstrom Bank, Nordstrom fsb", "City": "Centennial", "State": "Colorado", "Type of breach": "DISC", "Type of organization": "BSF", "Total Records": 2457, "Description of incident": "A total of 2,457 Nordstrom fsb customers in California were affected by a mailing error caused by an administrative error. \u00a0Cardholder statements, replacement credit cards, or other correspondence were mistakenly sent to addresses other than those of intended cardholders. The issue was discovered on June 7 and was the result of an attempt to reformat addresses to U.S. Postal Service standards. \u00a0Those who were affected were notified in June and July.", "Information Source": "California Attorney General", "Source URL": "", "Year of Breach": 2012, "Latitude": 39.580745, "Longitude": -104.877173}