{"Date Made Public": "2014-04-18", "date": "2014-04-18", "Company": "Willis North America Inc. Medical Expense Benefit Plan", "City": "", "State": "Maryland", "Type of breach": "DISC", "Type of organization": "MED", "Total Records": 129, "Description of incident": "name, dob, ssn, employee ID number Location of breached information: email Business associate present: No ", "Information Source": "Maryland Attorney General", "Source URL": "http://www.marylandattorneygeneral.gov/Pages/IdentityTheft/breachnotices.aspx", "Year of Breach": 2014, "Latitude": 39.045755, "Longitude": -76.641271}