{"Date Made Public": "2016-06-13", "date": "2016-06-13", "Company": "Momentum for Mental Health", "City": "San Jose", "State": "California", "Type of breach": "HACK", "Type of organization": "MED", "Total Records": 0, "Description of incident": "\"On June 3, 2016, Momentum was targeted by an e-mail scam called \"spoofing\".  We discovered this incident within hours of it taking place.  Nonetheless, it resulted in Momentum inadvertently making person information from your Form W-2 available to an unknown third party.\"The information compromised included Social Security numbers, information, wage information, tax deductions.More Information: http://oag.ca.gov/ecrime/databreach/reports/sb24-62338", "Information Source": "California Attorney General", "Source URL": "", "Year of Breach": 2016, "Latitude": 37.377897, "Longitude": -121.836571}