{"Date Made Public": "2013-02-25", "date": "2013-02-25", "Company": "Sprouts", "City": "Phoenix", "State": "Arizona", "Type of breach": "CARD", "Type of organization": "BSR", "Total Records": 0, "Description of incident": "A number of credit card terminals in 19 California and Arizona stores were affected by point-of-sale malware between January 25 and 29. \u00a0Credit card and debit card numbers were exposed. \u00a0Customer PINs associated with the payment cards were not affected. Sprouts identified the issue within a few days of the breach and updated customer information protection procedures in all of its stores.", "Information Source": "Media", "Source URL": "", "Year of Breach": 2013, "Latitude": 33.448377, "Longitude": -112.074037}