{"Date Made Public": "2013-03-19", "date": "2013-03-19", "Company": "General Services Administration (GSA)", "City": "Washington", "State": "District Of Columbia", "Type of breach": "DISC", "Type of organization": "GOV", "Total Records": 0, "Description of incident": "GSA users may have been able to view the financial information and trade secrets of other GSA users due to a security vulnerability. \u00a0The specific database that was affected is called the System for Award Management (SAM). \u00a0Contractor and vendor registration records are cataloged by SAM. \u00a0It is not clear how GSA became aware of the issue or how long it was a problem. \u00a0Agency officials revealed that users could purposefully or inadvertently view the information of other users after following a series of steps.UPDATE\u00a0(03/23/2013): \u00a0Users had Social Security numbers and tax identification numbers exposed.", "Information Source": "Media", "Source URL": "", "Year of Breach": 2013, "Latitude": 38.907192, "Longitude": -77.036871}