{"Date Made Public": "2013-04-26", "date": "2013-04-26", "Company": "LivingSocial", "City": "Washington", "State": "District Of Columbia", "Type of breach": "HACK", "Type of organization": "BSO", "Total Records": 29000000, "Description of incident": "As many as 50 million LivingSocial members may have had their names, email addresses, dates of birth, and encrypted passwords exposed by a cyber attack. \u00a0Customer credit card information was not compromised. \u00a0Customers were encouraged to change their passwords on any other sites on which they used the same or similar passwords.UPDATE\u00a0(05/03/2013): As many as 50 million acounts may have been affected. \u00a0It is estimated that 29 million people used LivingSocial and many had multiple accounts.", "Information Source": "Media", "Source URL": "", "Year of Breach": 2013, "Latitude": 38.907192, "Longitude": -77.036871}