{"Date Made Public": "2013-06-24", "date": "2013-06-24", "Company": "Florida State University, Florida Department of Education", "City": "Tallahassee", "State": "Florida", "Type of breach": "DISC", "Type of organization": "EDU", "Total Records": 47000, "Description of incident": "The information of 47,000 Florida teachers was publicly accessible for 14 days after a data transfer at Florida State University. \u00a0The information was from teachers participating in state prep programs. \u00a0The Department of Education used Florida State University as the contractor for the transfer of teacher data.UPDATE\u00a0(06/26/2013): People who participated in Florida teacher preparation programs during the 2009 -2010 and 2011-2012 academic years were affected.", "Information Source": "Media", "Source URL": "", "Year of Breach": 2013, "Latitude": 30.438256, "Longitude": -84.280733}