{"Date Made Public": "2013-10-22", "date": "2013-10-22", "Company": "Seton McCarthy Clinic, Seton Healthcare Family", "City": "Austin", "State": "Texas", "Type of breach": "PORT", "Type of organization": "MED", "Total Records": 5500, "Description of incident": "The clinic theft of a laptop on October 4 resulted in the exposure of patient information. \u00a0The stolen laptop contained names, Social Security numbers, addresses, phone numbers, dates of birth, Seton medical record numbers, patient account numbers, diagnosis information, immunization information, and insurance information of patients who visited the Seton Total Health Partners program, Seton McCarthy, Seton Topfer, and Seton Kozmetsky community health centers.", "Information Source": "Media", "Source URL": "", "Year of Breach": 2013, "Latitude": 30.267153, "Longitude": -97.743061}