{"Date Made Public": "2013-10-31", "date": "2013-10-31", "Company": "Boone Hospital Center", "City": "Columbia", "State": "Missouri", "Type of breach": "INSD", "Type of organization": "MED", "Total Records": 125, "Description of incident": "An employee was found to have accessed Social Security numbers, dates of birth, medical diagnoses, prescribed treatments, and other health information without cause. \u00a0A patient contacted Boone Hospital Center on September 16 and said that her personal health information had been accessed. \u00a0An investigation revealed the breach and the employee's access was terminated on September 19.", "Information Source": "Media", "Source URL": "", "Year of Breach": 2013, "Latitude": 38.951705, "Longitude": -92.334072}