{"Date Made Public": "2013-12-04", "date": "2013-12-04", "Company": "ADP, Facebook, Gmail, LinkedIn, Twitter, Yahoo, YouTube", "City": "", "State": "", "Type of breach": "HACK", "Type of organization": "BSO", "Total Records": 2000000, "Description of incident": "A breach that involved keylogging software affected at least 93,000 websites. \u00a0The virus may have originated on a server located in the Netherlands. \u00a0It first started collecting passwords and usernames on October 21. Approximately 860 computers in the United States were affected. More than 99% of the computers that were affected were outside of the United States.", "Information Source": "Media", "Source URL": "", "Year of Breach": 2013, "Latitude": 37.09024, "Longitude": -95.712891}