{"Date Made Public": "2017-01-20", "date": "2017-01-20", "Company": "Wonderful Center for Health Innovation", "City": "Lost Hills", "State": "California", "Type of breach": "PORT", "Type of organization": "MED", "Total Records": 0, "Description of incident": "\" On December 12, 2016, it was discovered that a laptop containing medical information from the Wonderful Center for Health Innovation was stolen between December 9, 2016 and December 12, 2016.\u00a0 We promptly reported the incident to law enforcement, and we continue to cooperate with the authorities.\u00a0 Unfortunately, the laptop has not yet been recovered.The files on the laptop included your full name, home address, date of birth, telephone number, electronic mail (email) address, clinic account number, medical conditions, medical test results, and clinic treatment date (s). We have no received an indication that information on the laptop has been accessed or used by an unauthorized individual, but wanted to alert you of this issue.\"More information: https://oag.ca.gov/ecrime/databreach/reports/sb24-65961", "Information Source": "California Attorney General", "Source URL": "", "Year of Breach": 2017, "Latitude": 35.616349, "Longitude": -119.694294}