{"Date Made Public": "2016-10-21", "date": "2016-10-21", "Company": "City of Middletown", "City": "Middleton", "State": "New York", "Type of breach": "HACK", "Type of organization": "GOV", "Total Records": 0, "Description of incident": "\"The city said Friday that computer hackers gained access to personal information of people who had contact with the Middletown Police Department. While an investigation has found no evidence of fraudulent misuse of personal information, the city of notifying those potentially affected by the breach and offering them free credit-monitoring and identity-restoration service.The FBI notified the city on June 15 that it discovered that part of the city's computer network might have been compromised.An investigation by the city, the FBI, state police, the state Office of Information Technology Services and forensics experts found one or more unauthorized people gained access to the database and were able to export at least a portion of the information.The potentially accessible data includes names, Social Security numbers, driver's license numbers, dates of birth fingerprints and addresses.\u00a0 The investigation found no evidence the information was publicly displayed or distributed, and the city is unaware of any fraudulent misuse of personal data.\"More Information: http://www.recordonline.com/news/20161021/hackers-breach-city-of-middlet...\u00a0\u00a0", "Information Source": "Media", "Source URL": "", "Year of Breach": 2016, "Latitude": 43.097217, "Longitude": -89.504288}