{"Date Made Public": "2018-10-22", "date": "2018-10-22", "Company": "The Centers for Medicare and Medicaid Services -", "City": "Baltimore", "State": "Maryland", "Type of breach": "HACK", "Type of organization": "GOV", "Total Records": 75000, "Description of incident": "According to the press release on their website, \"Earlier this week, CMS staff detected anomalous activity in the Federally Facilitated Exchanges, or FFE\u2019s Direct Enrollment pathway for agents and brokers. The Direct Enrollment pathway, first launched in 2013, allows agents and brokers to assist consumers with applications for coverage in the FFE. At this time, we believe that approximately 75,000 individuals\u2019 files were accessed. While this is a small fraction of consumer records present on the FFE, any breach of our system is unacceptable.\"\u00a0", "Information Source": "Media", "Source URL": "https://www.cms.gov/newsroom/press-releases/cms-responding-suspicious-activity-agent-and-broker-exchanges-portal", "Year of Breach": 2018, "Latitude": 0.0, "Longitude": 0.0}