{"Date Made Public": "2009-01-21", "date": "2009-01-21", "Company": "First Interstate Mortgage Corporation (FIM),  Nevada One Corporation (Nevada One)", "City": "", "State": "Nevada", "Type of breach": "PHYS", "Type of organization": "BSF", "Total Records": 0, "Description of incident": "These mortgage brokers have discarding consumers' tax returns, credit reports, and other sensitive personal and financial information in an unsecured dumpster in December of 2006. Approximately 40 boxes containing consumer records were found in a publicly-accessible dumpster. The records included tax returns, mortgage applications, bank statements, photocopies of credit cards, drivers' licenses, and at least 230 credit reports. The defendant, who has owned numerous companies that handle sensitive consumer information, kept the documents in an insecure manner in his garage before improperly disposing of them.UPDATE (1/20/10): The mortgage broker paid a $35,000 civil penalty to settle FTC charges. The mortgage broker will also have to hire an independent security professional to review the security process every year for 10 years.\u00a0", "Information Source": "NAID", "Source URL": "", "Year of Breach": 2009, "Latitude": 38.80261, "Longitude": -116.419389}