{"Date Made Public": "2017-03-14", "date": "2017-03-14", "Company": "Zest Dental Solutions", "City": "Carlsbad", "State": "California", "Type of breach": "HACK", "Type of organization": "BSO", "Total Records": 0, "Description of incident": "What HappenedWe began an investigation of our systems after reports from some customers receiving unusual emails containing Zest Dental purchase information. We engaged a computer security firm to examine our systems for any signs of an issue.\u00a0 On February 16, 2017, we learned that an unauthorized entity had compromised our e-commerce system potentially affecting customer payment card information. What Information Was InvolvedThe information compromised by the attack may have included your name, billing address, phone number, payment card number, expiration date, and CVV number from payment cards used for online transactions on Zest Dental's\u00a0 website between December 31, 2013 and September 21, 2014, and between November 2, 2016 and February 4, 2017.\"More Information: https://oag.ca.gov/ecrime/databreach/reports/sb24-66908", "Information Source": "California Attorney General", "Source URL": "", "Year of Breach": 2017, "Latitude": 33.131928, "Longitude": -117.248542}