{"Date Made Public": "2011-09-02", "date": "2011-09-02", "Company": "Pacific Retina Specialists", "City": "Seattle", "State": "Washington", "Type of breach": "INSD", "Type of organization": "MED", "Total Records": 60, "Description of incident": "At least 60 patients had their records stolen by a billing technician during late 2010. \u00a0The information included names, Social Security numbers, dates of birth, addresses and health insurance policy numbers. \u00a0Many patients who used Medicare Advantage plans at the clinic were affected. \u00a0The former employee and an accomplice also forged the names of three doctors on prescription forms. \u00a0The patient prescription information was then used to obtain narcotic prescription drugs worth thousands of dollars. \u00a0The former employee was sentenced to five years in prison. \u00a0", "Information Source": "PHIPrivacy.net", "Source URL": "", "Year of Breach": 2011, "Latitude": 47.60621, "Longitude": -122.332071}