{"Date Made Public": "2011-09-28", "date": "2011-09-28", "Company": "Atlanta Perinatal Associates", "City": "", "State": "", "Type of breach": "INSD", "Type of organization": "MED", "Total Records": 0, "Description of incident": "A former employee hacked into APA's database, copied patient information, and deleted APA's list. \u00a0It is not clear exactly how the former employee was able to access the database, but the purpose was to benefit the former employee's new employer. \u00a0Names, telephone numbers, and addresses of APA patients were taken. \u00a0APA's competitor, SeeBaby, used the information to create a direct-mail marketing list.UPDATE\u00a0(1/10/2012): The former employee was sentenced to serve 13 months in prison for hacking into the competitor's computer in order to lure away patients. \u00a0", "Information Source": "PHIPrivacy.net", "Source URL": "", "Year of Breach": 2011, "Latitude": 37.09024, "Longitude": -95.712891}