{"Date Made Public": "2012-01-27", "date": "2012-01-27", "Company": "Preferred Skin Solutions", "City": "Tulsa", "State": "Oklahoma", "Type of breach": "PORT", "Type of organization": "MED", "Total Records": 400, "Description of incident": "An office burglary that occurred on or around January 24 resulted in the loss of a laptop. The laptop held client records. \u00a0The company sent a breach notification through Facebook and email. \u00a0No financial information was on the laptop, but Preferred Skin Solutions still warned their clients about the risk of identity theft.", "Information Source": "PHIPrivacy.net", "Source URL": "", "Year of Breach": 2012, "Latitude": 36.153982, "Longitude": -95.992775}