{"Date Made Public": "2016-01-13", "date": "2016-01-13", "Company": "JB Autosports.com", "City": "Des Moines", "State": "Iowa", "Type of breach": "HACK", "Type of organization": "BSO", "Total Records": 0, "Description of incident": "\"You are a valued customer of JB Autosports, Inc., which is why you are receiving this notice about a security breach at http://subispeed.com and http://ft86speedfactory.com (\u201cthe websites\u201d) that may have affected your personal information.\u00a0 \u00a0From approximately August 1, 2015 through November 9, 2015, the websites\u2019 checkout page where customers input their payment information to purchase products from JB Autosports was the target of a cyberattack originating from a Russian IP address. The breach affected customers who used Visa, MasterCard, Discover, and American Express branded cards to pay for their purchases from the websites. The breach allowed cyberattackers to intercept customer names, addresses, credit card numbers, credit card expiration dates, CID numbers, CAV2 numbers, CVC2 numbers, and CVV2 numbers (\u201cCustomer Information\u201d). The Customer Information was intercepted after it was entered on the checkout page as it was being transmitted to PayPal for processing. JB Autosports\u2019 policy is to not store customer credit card information.\"", "Information Source": "Vermont Attorney General", "Source URL": "http://ago.vermont.gov/assets/files/Consumer/Security_Breach/JB%20Autosports%20Notice%20to%20Consumers.pdf", "Year of Breach": 2016, "Latitude": 41.609761, "Longitude": -93.617782}