{"Date Made Public": "2012-11-19", "date": "2012-11-19", "Company": "American Tool Supply (ATS)", "City": "Suwanee", "State": "Georgia", "Type of breach": "HACK", "Type of organization": "BSR", "Total Records": 617, "Description of incident": "A hacker gained\u00a0access to the ATS system and may have accessed financial information. \u00a0The attack was discovered on August 1 and financial information was immediately removed from the ATS online system. \u00a0", "Information Source": "California Attorney General", "Source URL": "", "Year of Breach": 2012, "Latitude": 34.05149, "Longitude": -84.0713}