{"Date Made Public": "2017-11-13", "date": "2017-11-13", "Company": "Gary W. Janke", "City": "Northridge", "State": "California", "Type of breach": "PHYS", "Type of organization": "BSF", "Total Records": 0, "Description of incident": "\"What happened and what information was involved:On the night of September 26, 2017, a thief broke into the back of the office building in Northridge, California.The building security alarms went off and the Los Angeles Police Department was dispatched. There is video of the thief in the offices and prints were recovered. However, before the first officers arrived, the thief stole a number of items from various offices in the building. Unfortunately, he stole two old computers from my offices. The computers contained tax information from 2012 and prior year tax returns that I had prepared. The data on the computers contained your personal information, including your name(s), address, Social Security number(s) and date of birth. It also included dependent information including name, social security number and date of birth. (For business clients, the data would have included federal identification numbers.) Your tax return information regarding income amounts andsources was also contained on the computers. If you were having your refunds directly deposited into your bank account, the bank account information would have been on one computer. Otherwise, your financial account numbers would not be part of the information stored. Copies of your W-2s and other financial documents were not scanned onto the computers. Please keep in mind that the information stolen was from 2012 and prior income tax returns.\"", "Information Source": "California Attorney General", "Source URL": "https://oag.ca.gov/ecrime/databreach/reports/sb24-104191", "Year of Breach": 2017, "Latitude": 34.249919, "Longitude": -118.503187}