{"Date Made Public": "2010-07-02", "date": "2010-07-02", "Company": "AMR Corporation", "City": "Fort Worth", "State": "Texas", "Type of breach": "STAT", "Type of organization": "BSO", "Total Records": 79000, "Description of incident": "Retirees, current, and former employees who participated in AMR's pension plan may have had their names, Social Security numbers, addresses, dates of birth, and other personal information stolen by the theft of a hard drive containing microfilm files.  Employees and beneficiaries of employees who were enrolled between 1960 and 1995 are at risk.", "Information Source": "Databreaches.net", "Source URL": "", "Year of Breach": 2010, "Latitude": 32.725409, "Longitude": -97.32085}